investogator-0.1.dist-info/DESCRIPTION.rst
investogator-0.1.dist-info/METADATA
investogator-0.1.dist-info/RECORD
investogator-0.1.dist-info/WHEEL
investogator-0.1.dist-info/entry_points.txt
investogator-0.1.dist-info/metadata.json
investogator-0.1.dist-info/top_level.txt
investogator_cli/__init__.py
investogator_cli/investogator_cli.py
investogator_cli/exceptions/__init__.py
