Metadata-Version: 2.0
Name: investogator
Version: 0.1
Summary: A CLI tool used to query and cross-reference data on stock-tracking sites based on ETF symbols
Home-page: UNKNOWN
Author: Ashley Dumaine
Author-email: ashley.dumaine@gmail.com
License: UNKNOWN
Platform: UNKNOWN
Requires-Dist: beautifulsoup4
Requires-Dist: requests
Requires-Dist: Click
